ioos_qc/__init__.py
ioos_qc/_version.py
ioos_qc/argo.py
ioos_qc/axds.py
ioos_qc/config.py
ioos_qc/gliders.py
ioos_qc/plotting.py
ioos_qc/qartod.py
ioos_qc/results.py
ioos_qc/stores.py
ioos_qc/streams.py
ioos_qc/utils.py
ioos_qc/config_creator/__init__.py
ioos_qc/config_creator/config_creator.py
ioos_qc/config_creator/fx_parser.py
ioos_qc/config_creator/get_assets.py
ioos_qc/config_creator/make_config.py
ioos_qc-2.2.1.dist-info/licenses/LICENSE.txt
ioos_qc-2.2.1.dist-info/METADATA
ioos_qc-2.2.1.dist-info/WHEEL
ioos_qc-2.2.1.dist-info/top_level.txt
ioos_qc-2.2.1.dist-info/RECORD
