Metadata-Version: 2.4
Name: ioos-qc
Version: 2.2.1
Summary: IOOS QARTOD and Quality Control tests implemented in Python
Maintainer-email: Kyle Wilcox <kyle@axds.co>, Filipe Fernandes <ocefpaf+ioos_qc@gmail.com>
License: Apache License
Project-URL: documentation, https://ioos.github.io/ioos_qc
Project-URL: homepage, https://github.com/ioos/ioos_qc
Project-URL: repository, https://github.com/ioos/ioos_qc
Classifier: Programming Language :: Python :: 3 :: Only
Classifier: Programming Language :: Python :: 3.9
Classifier: Programming Language :: Python :: 3.10
Classifier: Programming Language :: Python :: 3.11
Classifier: Programming Language :: Python :: 3.12
Classifier: Programming Language :: Python :: 3.13
Requires-Python: >=3.9
License-File: LICENSE.txt
Requires-Dist: geographiclib
Requires-Dist: geojson
Requires-Dist: h5netcdf
Requires-Dist: jsonschema
Requires-Dist: numpy>=1.14
Requires-Dist: pandas
Requires-Dist: pyparsing
Requires-Dist: ruamel.yaml
Requires-Dist: scipy
Requires-Dist: shapely
Requires-Dist: xarray>2022.03
Provides-Extra: extras
Requires-Dist: bokeh; extra == "extras"
Requires-Dist: nco; extra == "extras"
Requires-Dist: numba; extra == "extras"
Provides-Extra: test
Requires-Dist: dask; extra == "test"
Requires-Dist: pytest; extra == "test"
Dynamic: license-file
